[
  {
    "Id": 1,
    "bookingId": 1,
    "guestName": "Sarah Johnson",
    "roomNumber": "101",
    "amount": 245.00,
    "method": "card",
    "cardLastFour": "4567",
    "cardBrand": "Visa",
    "status": "completed",
    "transactionId": "TXN_2024_001",
    "processedAt": "2024-01-15T10:30:00Z",
    "items": [
      { "description": "Room Charge (2 nights)", "amount": 180.00 },
      { "description": "Resort Fee", "amount": 35.00 },
      { "description": "Taxes", "amount": 30.00 }
    ]
  },
  {
    "Id": 2,
    "bookingId": 2,
    "guestName": "Michael Chen",
    "roomNumber": "205",
    "amount": 320.00,
    "method": "card",
    "cardLastFour": "8912",
    "cardBrand": "Mastercard",
    "status": "completed",
    "transactionId": "TXN_2024_002",
    "processedAt": "2024-01-15T14:22:00Z",
    "items": [
      { "description": "Room Charge (3 nights)", "amount": 270.00 },
      { "description": "Resort Fee", "amount": 35.00 },
      { "description": "Taxes", "amount": 15.00 }
    ]
  },
  {
    "Id": 3,
    "bookingId": 3,
    "guestName": "Emily Davis",
    "roomNumber": "312",
    "amount": 189.00,
    "method": "card",
    "cardLastFour": "2345",
    "cardBrand": "American Express",
    "status": "pending",
    "transactionId": "TXN_2024_003",
    "processedAt": "2024-01-15T16:45:00Z",
    "items": [
      { "description": "Room Charge (1 night)", "amount": 150.00 },
      { "description": "Resort Fee", "amount": 25.00 },
      { "description": "Taxes", "amount": 14.00 }
    ]
  },
  {
    "Id": 4,
    "bookingId": 4,
    "guestName": "Robert Wilson",
    "roomNumber": "408",
    "amount": 425.50,
    "method": "card",
    "cardLastFour": "7890",
    "cardBrand": "Visa",
    "status": "completed",
    "transactionId": "TXN_2024_004",
    "processedAt": "2024-01-14T09:15:00Z",
    "items": [
      { "description": "Room Charge (4 nights)", "amount": 360.00 },
      { "description": "Resort Fee", "amount": 40.00 },
      { "description": "Spa Services", "amount": 25.50 }
    ]
  },
  {
    "Id": 5,
    "bookingId": 5,
    "guestName": "Lisa Anderson",
    "roomNumber": "201",
    "amount": 156.75,
    "method": "card",
    "cardLastFour": "5678",
    "cardBrand": "Mastercard",
    "status": "failed",
    "transactionId": "TXN_2024_005",
    "processedAt": "2024-01-14T11:30:00Z",
    "items": [
      { "description": "Room Charge (1 night)", "amount": 130.00 },
      { "description": "Resort Fee", "amount": 20.00 },
      { "description": "Taxes", "amount": 6.75 }
    ]
  }
]